stilts_nli/__about__.py
stilts_nli/__init__.py
stilts_nli/__main__.py
stilts_nli/model/__init__.py
stilts_nli/model/basemodel.py
stilts_nli/model/gen_model.py
stilts_nli/model/parrot_model.py
stilts_nli/model/stilts_model.py
stilts_nli/utils/__init__.py
stilts_nli/utils/completion.py
stilts_nli-0.0.7.dist-info/METADATA
stilts_nli-0.0.7.dist-info/WHEEL
stilts_nli-0.0.7.dist-info/entry_points.txt
stilts_nli-0.0.7.dist-info/licenses/LICENSE
stilts_nli-0.0.7.dist-info/RECORD
