Metadata-Version: 2.4
Name: stilts-nli
Version: 0.0.7
Summary: A natural Language Interface to STILTS.
Project-URL: Documentation, https://github.com/RhysAlfShaw/stilts-nli#readme
Project-URL: Issues, https://github.com/RhysAlfShaw/stilts-nli/issues
Project-URL: Source, https://github.com/RhysAlfShaw/stilts-nli
Author-email: Rhys Shaw <rhysc3p0@gmail.com>
License-Expression: GPL-3.0-or-later
License-File: LICENSE
Classifier: Development Status :: 4 - Beta
Classifier: License :: OSI Approved :: GNU General Public License v3 or later (GPLv3+)
Classifier: Programming Language :: Python :: 3
Classifier: Programming Language :: Python :: 3.12
Requires-Python: >=3.12
Requires-Dist: accelerate
Requires-Dist: llama-cpp-python
Requires-Dist: numpy
Requires-Dist: prompt-toolkit
Requires-Dist: setproctitle
Requires-Dist: torch
Requires-Dist: transformers
